jcutils-0.3.2.dist-info/METADATA
jcutils-0.3.2.dist-info/WHEEL
jcutils/settings/__init__.py
jcutils/settings/model.py
jcutils/settings/config.toml
jcutils/__init__.py
jcutils/utils/logging_.py
jcutils/utils/kafka_client.py
jcutils/utils/geo.py
jcutils/utils/save_data.py
jcutils/utils/tool_threading.py
jcutils/utils/format_utils.py
jcutils/utils/htmlstrip.py
jcutils/utils/built_in_tools.py
jcutils/utils/dingtalk.py
jcutils/utils/os_platform.py
jcutils/utils/try_except_.py
jcutils/utils/run_log_time.py
jcutils/utils/os_path.py
jcutils/utils/nginx_log.py
jcutils/utils/pg_client.py
jcutils/utils/dingtalkoapi.py
jcutils/utils/s3_client.py
jcutils/utils/convert.py
jcutils/utils/tools.py
jcutils/utils/html.py
jcutils/utils/relative_time.py
jcutils/utils/ldap_client.py
jcutils/utils/__init__.py
jcutils/utils/tabulate_utils.py
jcutils/utils/holiday1.py
jcutils/utils/apscheduler_.py
jcutils/utils/platform_.py
jcutils/utils/lazy_import.py
jcutils/utils/regeo.py
jcutils/utils/geapi.py
jcutils/utils/qiniu_api.py
jcutils/utils/utils.py
jcutils/utils/run_func_time.py
jcutils/utils/tornado_log.py
jcutils/utils/run_time.py
jcutils/utils/date_encoder.py
jcutils/utils/test.db
jcutils/utils/run_line_time.py
jcutils/utils/datetime_.py
jcutils/utils/ftp_client.py
jcutils/utils/Tool.py
jcutils/utils/holiday.py
jcutils/client/kafka_client.py
jcutils/client/work_weixin_send.py
jcutils/client/hdfs_client.py
jcutils/client/imaplib_client.py
jcutils/client/mssql_client_pool.py
jcutils/client/work_weixin_api.py
jcutils/client/mysql_client.py
jcutils/client/work_weixin_bot.py
jcutils/client/PyodbcClient.py
jcutils/client/pg_client.py
jcutils/client/mssql_client.py
jcutils/client/pykafka_client.py
jcutils/client/ldap_client.py
jcutils/client/__init__.py
jcutils/client/dataworks_client.py
jcutils/client/hbase_client.py
jcutils/client/weixin_offiaccount.py
jcutils/client/redis_client.py
jcutils/client/presto_client.py
jcutils/client/mongo_client.py
jcutils/client/maxcompute_client.py
jcutils/client/mysql_client_pool.py
jcutils/client/hive_client.py
jcutils-0.3.2.dist-info/RECORD
