Metadata-Version: 2.3
Name: jcutils
Version: 0.3.2
Classifier: Programming Language :: Python :: 3
Classifier: License :: OSI Approved :: MIT License
Classifier: Operating System :: OS Independent
Requires-Dist: apscheduler ~=3.10.1
Requires-Dist: clickhouse-driver ==0.2.6
Requires-Dist: fastapi ==0.70.1
Requires-Dist: ldap3 ==2.9.1
Requires-Dist: numpy <2
Requires-Dist: pymysql ==1.0.2
Requires-Dist: pyodps ==0.11.6.1
Requires-Dist: pyquery ==2.0.0
Requires-Dist: python-dateutil ==2.8.2
Requires-Dist: python-multipart ==0.0.5
Requires-Dist: redis ==3.5.3
Requires-Dist: requests ==2.26.0
Requires-Dist: retry ==0.9.2
Requires-Dist: sentry-sdk ~=1.21.0
Requires-Dist: uvicorn ==0.16.0
Requires-Dist: huaweicloudsdkdli ==3.1.19
Requires-Dist: redis-py-cluster ==2.1.3
Requires-Dist: dbutils ==3.0.2
Requires-Dist: pyquery ~=2.0.0
Requires-Dist: imbox ~=0.9.8
Requires-Dist: happybase ~=1.2.0
Requires-Dist: easybase ~=1.1.3
Requires-Dist: urllib3 ~=1.26.15
Requires-Dist: chardet ~=4.0.0
Requires-Dist: func-timeout ~=4.3.5
Requires-Dist: fire >=0.5.0
Requires-Dist: esdk-obs-python >=3.23.9.1
Requires-Dist: alibabacloud-ecs20140526 >=3.0.12
Requires-Dist: alibabacloud-dataworks-public20200518 >=4.7.2
Requires-Dist: alibabacloud-maxcompute20220104 >=2.3.0
Requires-Dist: pandas >=2.2.2
Requires-Dist: openpyxl >=3.1.5
Requires-Dist: rich >=13.7.1
Requires-Dist: tabulate[widechars] >=0.9.0
Requires-Dist: wcwidth >=0.2.13
Requires-Dist: kafka-python
Requires-Dist: toml >=0.10.2
Requires-Dist: datamodel-code-generator >=0.25.9
Summary: python utils
Keywords: utils,toolkit,tools,python
Author-email: lijc210 <lijc210@163.com>
License: MIT License
Requires-Python: >=3.8
Project-URL: Homepage, https://github.com/lijc210/jcutils
Project-URL: Documentation, https://github.com/lijc210/jcutils
Project-URL: Source, https://github.com/lijc210/jcutils
Project-URL: Tracker, https://github.com/lijc210/jcutils/issues
